{"stats":{"minecraft:dropped":{"minecraft:piston":8,"minecraft:birch_planks":2,"minecraft:oak_pressure_plate":1,"minecraft:cooked_beef":9,"minecraft:cooked_porkchop":4,"minecraft:rail":40,"minecraft:dirt":207,"minecraft:pumpkin_pie":14,"minecraft:bone_meal":2,"minecraft:iron_pickaxe":5,"minecraft:white_wool":1,"minecraft:gravel":4,"minecraft:stone_axe":1,"minecraft:sugar_cane":4,"minecraft:wheat":1,"minecraft:rotten_flesh":8,"minecraft:oak_planks":12,"minecraft:white_bed":11,"minecraft:salmon":9,"minecraft:poppy":12,"minecraft:oak_fence_gate":3,"minecraft:leather_boots":1,"minecraft:chest":1,"minecraft:ladder":1,"minecraft:powered_rail":2,"minecraft:glass":83,"minecraft:acacia_fence":3,"minecraft:iron_ingot":11,"minecraft:bread":194,"minecraft:oak_slab":1,"minecraft:wheat_seeds":130,"minecraft:minecart":3,"minecraft:oak_fence":16,"minecraft:cobblestone":241,"minecraft:lead":1,"minecraft:stick":25,"minecraft:torch":47,"minecraft:iron_leggings":1,"minecraft:iron_axe":2,"minecraft:iron_shovel":1,"minecraft:acacia_planks":32,"minecraft:dandelion":1,"minecraft:redstone_block":2,"minecraft:redstone":61,"minecraft:furnace":1,"minecraft:diamond_hoe":1,"minecraft:clay_ball":1,"minecraft:shears":1,"minecraft:shield":2,"minecraft:iron_chestplate":1,"minecraft:diamond_pickaxe":5,"minecraft:light_gray_bed":12,"minecraft:oak_boat":1,"minecraft:spider_eye":1,"minecraft:wooden_pickaxe":1},"minecraft:crafted":{"minecraft:smooth_stone":8,"minecraft:oak_planks":684,"minecraft:cooked_chicken":9,"minecraft:stone":8,"minecraft:cobblestone_stairs":32,"minecraft:lever":1,"minecraft:diamond_shovel":1,"minecraft:bookshelf":7,"minecraft:cooked_mutton":5,"minecraft:iron_bars":16,"minecraft:glass":166,"minecraft:bow":1,"minecraft:iron_boots":1,"minecraft:chest":13,"minecraft:acacia_fence":15,"minecraft:oak_fence":180,"minecraft:polished_diorite_slab":54,"minecraft:smoker":1,"minecraft:white_banner":1,"minecraft:cooked_porkchop":3,"minecraft:diamond_axe":1,"minecraft:crafting_table":6,"minecraft:baked_potato":6,"minecraft:iron_helmet":1,"minecraft:wooden_pickaxe":1,"minecraft:birch_planks":64,"minecraft:pumpkin_seeds":56,"minecraft:campfire":6,"minecraft:light_gray_bed":20,"minecraft:diamond_pickaxe":2,"minecraft:iron_chestplate":2,"minecraft:book":22,"minecraft:paper":216,"minecraft:shield":1,"minecraft:stick":284,"minecraft:iron_ingot":117,"minecraft:iron_pickaxe":8,"minecraft:acacia_door":3,"minecraft:gold_ingot":13,"minecraft:light_gray_dye":8,"minecraft:redstone_torch":3,"minecraft:polished_andesite":116,"minecraft:oak_door":3,"minecraft:redstone":27,"minecraft:fishing_rod":1,"minecraft:iron_nugget":180,"minecraft:diamond_hoe":1,"minecraft:furnace":6,"minecraft:blast_furnace":4,"minecraft:light_gray_wool":8,"minecraft:gray_dye":4,"minecraft:bone_meal":45,"minecraft:glass_pane":144,"minecraft:lantern":22,"minecraft:polished_diorite":60,"minecraft:iron_axe":2,"minecraft:cobblestone_wall":54,"minecraft:cooked_beef":29,"minecraft:coal_block":3,"minecraft:sugar":102,"minecraft:cooked_cod":1,"minecraft:diamond_sword":1,"minecraft:enchanting_table":1,"minecraft:iron_sword":1,"minecraft:bowl":4,"minecraft:acacia_trapdoor":4,"minecraft:polished_granite":160,"minecraft:bucket":2,"minecraft:bread":246,"minecraft:air":0,"minecraft:oak_fence_gate":3,"minecraft:white_dye":9,"minecraft:iron_shovel":4,"minecraft:iron_leggings":2,"minecraft:white_bed":21,"minecraft:pumpkin_pie":80,"minecraft:acacia_planks":204,"minecraft:torch":204},"minecraft:picked_up":{"minecraft:wooden_axe":1,"minecraft:iron_chestplate":2,"minecraft:wheat":983,"minecraft:redstone_block":33,"minecraft:stone_slab":6,"minecraft:lead":14,"minecraft:string":47,"minecraft:iron_leggings":2,"minecraft:pufferfish":2,"minecraft:blue_stained_glass_pane":24,"minecraft:oak_sign":3,"minecraft:beetroot":172,"minecraft:sea_pickle":13,"minecraft:smooth_stone":28,"minecraft:bucket":1,"minecraft:redstone_torch":6,"minecraft:cobblestone_slab":13,"minecraft:iron_pickaxe":4,"minecraft:coal_block":1,"minecraft:furnace":5,"minecraft:stick":140,"minecraft:acacia_fence":2,"minecraft:oak_fence":141,"minecraft:torch":162,"minecraft:acacia_log":514,"minecraft:diorite":48,"minecraft:rabbit_foot":2,"minecraft:blue_stained_glass":4,"minecraft:stone_sword":1,"minecraft:cactus":69,"minecraft:light_gray_bed":4,"minecraft:rotten_flesh":65,"minecraft:blue_dye":1,"minecraft:obsidian":5,"minecraft:cod":2,"minecraft:cobblestone":2158,"minecraft:birch_log":37,"minecraft:feather":7,"minecraft:cooked_beef":9,"minecraft:andesite":156,"minecraft:smoker":2,"minecraft:potato":301,"minecraft:flint":11,"minecraft:lantern":8,"minecraft:dirt":1961,"minecraft:polished_granite":26,"minecraft:leather_boots":1,"minecraft:glass":128,"minecraft:bone":26,"minecraft:acacia_planks":2,"minecraft:bow":2,"minecraft:wheat_seeds":3128,"minecraft:powered_rail":14,"minecraft:oak_planks":29,"minecraft:cooked_porkchop":2,"minecraft:oak_pressure_plate":2,"minecraft:sand":467,"minecraft:ink_sac":2,"minecraft:mossy_cobblestone":1,"minecraft:polished_andesite":49,"minecraft:sugar":4,"minecraft:diamond":27,"minecraft:lever":11,"minecraft:granite":166,"minecraft:grass":10,"minecraft:bone_meal":27,"minecraft:bread":49,"minecraft:oak_sapling":13,"minecraft:diamond_pickaxe":4,"minecraft:fishing_rod":2,"minecraft:charcoal":4,"minecraft:crafting_table":7,"minecraft:azure_bluet":13,"minecraft:chicken":7,"minecraft:ladder":10,"minecraft:clay_ball":1,"minecraft:brown_mushroom":9,"minecraft:shield":4,"minecraft:cornflower":2,"minecraft:iron_axe":2,"minecraft:item_frame":5,"minecraft:glass_pane":72,"minecraft:blue_orchid":8,"minecraft:beef":29,"minecraft:oak_boat":2,"minecraft:iron_nugget":14,"minecraft:poppy":18,"minecraft:light_gray_wool":65,"minecraft:minecart":6,"minecraft:sugar_cane":645,"minecraft:chest":14,"minecraft:birch_sapling":1,"minecraft:diamond_hoe":2,"minecraft:piston":29,"minecraft:egg":383,"minecraft:carrot":690,"minecraft:redstone":565,"minecraft:arrow":51,"minecraft:cooked_cod":1,"minecraft:light_blue_stained_glass_pane":2,"minecraft:beetroot_seeds":476,"minecraft:pumpkin_pie":16,"minecraft:shears":2,"minecraft:mutton":5,"minecraft:white_wool":150,"minecraft:rail":91,"minecraft:salmon":8,"minecraft:leather":23,"minecraft:red_mushroom":19,"minecraft:birch_planks":5,"minecraft:oak_log":190,"minecraft:cobblestone_stairs":44,"minecraft:gunpowder":10,"minecraft:cobblestone_wall":50,"minecraft:white_banner":1,"minecraft:apple":3,"minecraft:acacia_trapdoor":3,"minecraft:iron_ingot":124,"minecraft:oak_fence_gate":19,"minecraft:cooked_chicken":3,"minecraft:iron_ore":108,"minecraft:iron_sword":4,"minecraft:acacia_sapling":96,"minecraft:oak_slab":2,"minecraft:pumpkin":195,"minecraft:dandelion":13,"minecraft:gravel":337,"minecraft:white_bed":12,"minecraft:gold_ore":47,"minecraft:spider_eye":14,"minecraft:diamond_shovel":2,"minecraft:pumpkin_seeds":5,"minecraft:polished_diorite":24,"minecraft:diamond_axe":1,"minecraft:coal":499,"minecraft:ender_pearl":1},"minecraft:mined":{"minecraft:white_bed":10,"minecraft:farmland":4,"minecraft:cobblestone_stairs":30,"minecraft:obsidian":5,"minecraft:granite":82,"minecraft:acacia_log":438,"minecraft:grass_block":892,"minecraft:light_gray_bed":3,"minecraft:polished_diorite":24,"minecraft:oak_wall_sign":1,"minecraft:light_blue_stained_glass":2,"minecraft:smooth_stone":16,"minecraft:iron_ore":108,"minecraft:pumpkin":131,"minecraft:azure_bluet":5,"minecraft:oak_sign":1,"minecraft:blue_orchid":8,"minecraft:tripwire":1,"minecraft:brown_mushroom":6,"minecraft:melon_stem":1,"minecraft:smoker":1,"minecraft:torch":70,"minecraft:poppy":7,"minecraft:chest":14,"minecraft:glass":9,"minecraft:cobblestone":454,"minecraft:sugar_cane":207,"minecraft:oak_planks":4,"minecraft:wall_torch":49,"minecraft:seagrass":2,"minecraft:acacia_sapling":1,"minecraft:powered_rail":17,"minecraft:birch_log":12,"minecraft:wheat":1019,"minecraft:pumpkin_stem":1,"minecraft:grass":467,"minecraft:oak_log":113,"minecraft:beetroots":158,"minecraft:acacia_fence":2,"minecraft:sand":351,"minecraft:dirt":462,"minecraft:piston":23,"minecraft:oak_leaves":88,"minecraft:light_blue_stained_glass_pane":1,"minecraft:diamond_ore":24,"minecraft:blue_stained_glass_pane":1,"minecraft:mossy_cobblestone":1,"minecraft:lever":8,"minecraft:ladder":11,"minecraft:red_mushroom":20,"minecraft:redstone_ore":82,"minecraft:furnace":4,"minecraft:carrots":186,"minecraft:acacia_trapdoor":3,"minecraft:andesite":113,"minecraft:potatoes":90,"minecraft:cobblestone_slab":5,"minecraft:rail":80,"minecraft:lantern":5,"minecraft:stone":1203,"minecraft:white_wool":18,"minecraft:redstone_wall_torch":3,"minecraft:oak_slab":1,"minecraft:acacia_leaves":38,"minecraft:redstone_block":29,"minecraft:glass_pane":17,"minecraft:dandelion":2,"minecraft:polished_granite":26,"minecraft:oak_fence":68,"minecraft:crafting_table":1,"minecraft:cornflower":2,"minecraft:campfire":2,"minecraft:diorite":43,"minecraft:birch_planks":4,"minecraft:cactus":3,"minecraft:cobblestone_wall":44,"minecraft:sea_pickle":3,"minecraft:redstone_torch":3,"minecraft:birch_leaves":4,"minecraft:grass_path":1,"minecraft:coal_ore":381,"minecraft:gravel":98,"minecraft:cobweb":16,"minecraft:polished_andesite":16,"minecraft:gold_ore":46},"minecraft:killed":{"minecraft:spider":13,"minecraft:skeleton":16,"minecraft:chicken":8,"minecraft:zombie_villager":1,"minecraft:salmon":4,"minecraft:iron_golem":4,"minecraft:creeper":7,"minecraft:sheep":2,"minecraft:trader_llama":1,"minecraft:pillager":1,"minecraft:zombie":37,"minecraft:cow":8,"minecraft:husk":1,"minecraft:bat":2,"minecraft:wandering_trader":1,"minecraft:squid":1},"minecraft:custom":{"minecraft:animals_bred":69,"minecraft:interact_with_crafting_table":195,"minecraft:open_barrel":66,"minecraft:bell_ring":1,"minecraft:leave_game":19,"minecraft:time_since_death":164575,"minecraft:sprint_one_cm":2074006,"minecraft:damage_blocked_by_shield":660,"minecraft:drop":331,"minecraft:talked_to_villager":23,"minecraft:deaths":2,"minecraft:jump":10262,"minecraft:walk_on_water_one_cm":132499,"minecraft:interact_with_furnace":89,"minecraft:play_one_minute":1028419,"minecraft:sleep_in_bed":50,"minecraft:damage_dealt":19836,"minecraft:crouch_one_cm":16805,"minecraft:interact_with_smoker":29,"minecraft:horse_one_cm":9242,"minecraft:mob_kills":108,"minecraft:climb_one_cm":23593,"minecraft:walk_one_cm":4358607,"minecraft:sneak_time":6448,"minecraft:walk_under_water_one_cm":67106,"minecraft:boat_one_cm":25038,"minecraft:interact_with_blast_furnace":43,"minecraft:interact_with_stonecutter":1,"minecraft:time_since_rest":58745,"minecraft:damage_taken":3661,"minecraft:minecart_one_cm":91535,"minecraft:swim_one_cm":71052,"minecraft:fly_one_cm":1483908,"minecraft:open_chest":856,"minecraft:fish_caught":2,"minecraft:fall_one_cm":170632},"minecraft:used":{"minecraft:beetroot":1,"minecraft:light_blue_stained_glass_pane":2,"minecraft:iron_shovel":783,"minecraft:ladder":5,"minecraft:diamond_hoe":83,"minecraft:oak_sign":4,"minecraft:chest":25,"minecraft:iron_sword":470,"minecraft:rotten_flesh":1,"minecraft:carrot":300,"minecraft:acacia_sapling":45,"minecraft:glass":59,"minecraft:lava_bucket":3,"minecraft:lantern":34,"minecraft:birch_sapling":1,"minecraft:item_frame":4,"minecraft:bow":14,"minecraft:furnace":5,"minecraft:cooked_cod":2,"minecraft:beetroot_seeds":211,"minecraft:acacia_fence":14,"minecraft:egg":4,"minecraft:potato":177,"minecraft:diorite":10,"minecraft:acacia_trapdoor":4,"minecraft:powered_rail":5,"minecraft:oak_planks":3,"minecraft:polished_diorite_slab":28,"minecraft:cactus":9,"minecraft:wooden_pickaxe":21,"minecraft:redstone_block":14,"minecraft:sugar_cane":66,"minecraft:diamond_axe":402,"minecraft:white_wool":20,"minecraft:sand":112,"minecraft:blast_furnace":4,"minecraft:shears":5,"minecraft:pumpkin_seeds":24,"minecraft:redstone_torch":8,"minecraft:lever":8,"minecraft:acacia_door":3,"minecraft:bread":44,"minecraft:string":1,"minecraft:polished_granite":70,"minecraft:diamond_sword":49,"minecraft:andesite":6,"minecraft:bone_meal":8,"minecraft:oak_fence":199,"minecraft:iron_bars":2,"minecraft:enchanting_table":1,"minecraft:acacia_log":269,"minecraft:stone_hoe":80,"minecraft:cooked_chicken":7,"minecraft:oak_door":4,"minecraft:torch":288,"minecraft:dirt":1423,"minecraft:cobblestone_wall":94,"minecraft:oak_fence_gate":1,"minecraft:granite":3,"minecraft:polished_diorite":41,"minecraft:bookshelf":7,"minecraft:iron_axe":485,"minecraft:melon_seeds":2,"minecraft:cooked_beef":19,"minecraft:light_gray_bed":9,"minecraft:pumpkin":2,"minecraft:wheat_seeds":1145,"minecraft:cooked_mutton":5,"minecraft:water_bucket":19,"minecraft:cobblestone_stairs":51,"minecraft:birch_planks":19,"minecraft:polished_andesite":78,"minecraft:sheep_spawn_egg":3,"minecraft:salmon":5,"minecraft:mossy_cobblestone":1,"minecraft:rail":25,"minecraft:crafting_table":7,"minecraft:white_bed":18,"minecraft:campfire":6,"minecraft:smoker":2,"minecraft:oak_log":12,"minecraft:piston":15,"minecraft:diamond_pickaxe":1133,"minecraft:apple":1,"minecraft:diamond_shovel":948,"minecraft:iron_pickaxe":1763,"minecraft:stone_axe":2,"minecraft:fishing_rod":5,"minecraft:cobblestone":1474,"minecraft:white_banner":1,"minecraft:cooked_porkchop":1,"minecraft:bucket":24,"minecraft:glass_pane":148,"minecraft:pumpkin_pie":26,"minecraft:sea_pickle":8,"minecraft:smooth_stone":4},"minecraft:broken":{"minecraft:iron_shovel":4,"minecraft:iron_sword":1,"minecraft:stone_hoe":1,"minecraft:iron_axe":2,"minecraft:iron_pickaxe":7}},"DataVersion":1976}